em_waves/__init__.py
em_waves/waves.py
em_waves-0.0.2.dist-info/LICENSE.txt
em_waves-0.0.2.dist-info/METADATA
em_waves-0.0.2.dist-info/WHEEL
em_waves-0.0.2.dist-info/top_level.txt
em_waves-0.0.2.dist-info/RECORD
