Metadata-Version: 2.1
Name: em-waves
Version: 0.0.2
Summary: Simulation of electromagnetic wave hitting an interface with a different medium.
Home-page: https://github.com/urbanij/em_waves
Author: Francesco Urbani
Author-email: francescourbanidue@gmail.com
License: LICENSE.txt
Keywords: electromagnetic waves,
Platform: UNKNOWN
Requires-Python: >=3.7
Requires-Dist: numpy (>=1.19.2)
Requires-Dist: matplotlib (>=3.3.2)
